balena_cloud/__init__.py
balena_cloud/balena_cloud.py
balena_cloud/exceptions.py
balena_cloud/models.py
balena_cloud/py.typed
balena_cloud-1.1.2.dist-info/METADATA
balena_cloud-1.1.2.dist-info/WHEEL
balena_cloud-1.1.2.dist-info/licenses/LICENSE
balena_cloud-1.1.2.dist-info/RECORD
