Metadata-Version: 2.4
Name: balena-cloud
Version: 1.1.2
Summary: Asynchronous Python client to interact with the Balena Cloud API
License-Expression: MIT
License-File: LICENSE
Keywords: balena-cloud,api,async,client
Author: Klaas Schoute
Author-email: <klaas@mrgreenoffices.nl>
Maintainer: Klaas Schoute
Maintainer-email: <klaas@mrgreenoffices.nl>
Requires-Python: >=3.11
Classifier: Framework :: AsyncIO
Classifier: Intended Audience :: Developers
Classifier: Natural Language :: English
Classifier: Programming Language :: Python :: 3.11
Classifier: Programming Language :: Python :: 3.12
Classifier: Programming Language :: Python :: 3.13
Classifier: Programming Language :: Python :: 3.14
Classifier: Programming Language :: Python :: 3
Classifier: Topic :: Software Development :: Libraries :: Python Modules
Requires-Dist: aiohttp (>=3.13.0,<4.0.0)
Requires-Dist: mashumaro (>=3.17,<4.0)
Requires-Dist: orjson (>=3.11.3,<4.0.0)
Requires-Dist: yarl (>=1.22.0,<2.0.0)
Project-URL: Bug Tracker, https://github.com/MrGreenBoutiqueOffices/python-balena-cloud/issues
Project-URL: Changelog, https://github.com/MrGreenBoutiqueOffices/python-balena-cloud/releases
Project-URL: Documentation, https://github.com/MrGreenBoutiqueOffices/python-balena-cloud
Project-URL: Homepage, https://github.com/MrGreenBoutiqueOffices/python-balena-cloud
Project-URL: Repository, https://github.com/MrGreenBoutiqueOffices/python-balena-cloud
